README.rst
setup.cfg
setup.py
fit_neuron/__init__.py
fit_neuron.egg-info/PKG-INFO
fit_neuron.egg-info/SOURCES.txt
fit_neuron.egg-info/dependency_links.txt
fit_neuron.egg-info/top_level.txt
fit_neuron/data/__init__.py
fit_neuron/data/data_loader.py
fit_neuron/data/dl_neuron_data.py
fit_neuron/data/extract_spikes.py
fit_neuron/data/my_data.py
fit_neuron/evaluate/__init__.py
fit_neuron/evaluate/evaluate.py
fit_neuron/evaluate/spkd_lib.py
fit_neuron/optimize/__init__.py
fit_neuron/optimize/fit_gLIF.py
fit_neuron/optimize/neuron_base_obj.py
fit_neuron/optimize/sic_lib.py
fit_neuron/optimize/subthreshold.py
fit_neuron/optimize/threshold.py
fit_neuron/tests/__init__.py
fit_neuron/tests/test.py
fit_neuron/tests/test_load_neuron.py
fit_neuron/tests/test_model.py