Metadata-Version: 1.1
Name: fit-neuron
Version: 0.0.6
Summary: Package for estimation and evaluation of neural models from patch clamp neural recordings.
Home-page: http://pythonhosted.org/fit_neuron
Author: Nicolas D. Jimenez
Author-email: nicodjimenez@gmail.com
License: Apache
Keywords: neuron linear integrate and fire patch clamp fitting parameter estimation spike distance metrics
Platform: UNKNOWN
Classifier: Development Status :: 1 - Planning
Classifier: License :: Freely Distributable
Classifier: Intended Audience :: Science/Research
Classifier: Topic :: Scientific/Engineering :: Bio-Informatics
